biotmed_ums_sdk/__init__.py
biotmed_ums_sdk/api_client.py
biotmed_ums_sdk/api_response.py
biotmed_ums_sdk/configuration.py
biotmed_ums_sdk/exceptions.py
biotmed_ums_sdk/py.typed
biotmed_ums_sdk/rest.py
biotmed_ums_sdk/api/__init__.py
biotmed_ums_sdk/api/captcha_api_api.py
biotmed_ums_sdk/api/device_api_api.py
biotmed_ums_sdk/api/group_api_api.py
biotmed_ums_sdk/api/health_check_api_api.py
biotmed_ums_sdk/api/login_api_api.py
biotmed_ums_sdk/api/mfa_login_api_api.py
biotmed_ums_sdk/api/permission_api_api.py
biotmed_ums_sdk/api/role_api_api.py
biotmed_ums_sdk/api/security_api_api.py
biotmed_ums_sdk/api/self_permission_api_api.py
biotmed_ums_sdk/api/self_user_api_api.py
biotmed_ums_sdk/api/service_user_api_api.py
biotmed_ums_sdk/api/settings_api_api.py
biotmed_ums_sdk/api/sync_token_permissions_api_api.py
biotmed_ums_sdk/api/sync_token_permissions_core_api_api.py
biotmed_ums_sdk/api/temporary_credentials_api_api.py
biotmed_ums_sdk/api/temporary_token_operation_api_api.py
biotmed_ums_sdk/api/user_api_api.py
biotmed_ums_sdk/models/__init__.py
biotmed_ums_sdk/models/associate_permissions_to_role_admin_request.py
biotmed_ums_sdk/models/associate_roles_to_group_admin_request.py
biotmed_ums_sdk/models/create_group_admin_request.py
biotmed_ums_sdk/models/create_role_admin_request.py
biotmed_ums_sdk/models/create_secret_key_response.py
biotmed_ums_sdk/models/create_service_user_request.py
biotmed_ums_sdk/models/create_service_user_response.py
biotmed_ums_sdk/models/create_user_request.py
biotmed_ums_sdk/models/credentials.py
biotmed_ums_sdk/models/device_access_token_response.py
biotmed_ums_sdk/models/dissociate_permissions_from_role_admin_request.py
biotmed_ums_sdk/models/dissociate_roles_from_group_admin_request.py
biotmed_ums_sdk/models/error_response.py
biotmed_ums_sdk/models/filter_v2.py
biotmed_ums_sdk/models/forgot_password_request_v2.py
biotmed_ums_sdk/models/generate_otp_request.py
biotmed_ums_sdk/models/generate_otp_response.py
biotmed_ums_sdk-0.1.0.dist-info/METADATA
biotmed_ums_sdk-0.1.0.dist-info/WHEEL
biotmed_ums_sdk-0.1.0.dist-info/top_level.txt
biotmed_ums_sdk-0.1.0.dist-info/RECORD
